greetings/__init__.py
greetings/greetings.py
trantestpackage2024-0.0.1.dist-info/LICENCE.txt
trantestpackage2024-0.0.1.dist-info/METADATA
trantestpackage2024-0.0.1.dist-info/WHEEL
trantestpackage2024-0.0.1.dist-info/top_level.txt
trantestpackage2024-0.0.1.dist-info/RECORD
